biyoves/__init__.py
biyoves/corrector.py
biyoves/face_utils.py
biyoves/layout.py
biyoves/processor.py
biyoves/remove_bg.py
biyoves/models/2d106det.onnx
biyoves/models/det_500m.onnx
biyoves/models/modnet.onnx
biyoves-1.0.1.dist-info/licenses/LICENSE
biyoves-1.0.1.dist-info/METADATA
biyoves-1.0.1.dist-info/WHEEL
biyoves-1.0.1.dist-info/top_level.txt
biyoves-1.0.1.dist-info/RECORD
