Metadata-Version: 2.4
Name: biyoves
Version: 1.0.1
Summary: Yapay Zeka destekli Biyometrik, Vesikalık ve Vize fotoğrafları oluşturma kütüphanesi.
Author: BiyoVes
License: MIT
Project-URL: Homepage, https://github.com/aytugyuruk/biyoves
Project-URL: Documentation, https://github.com/aytugyuruk/biyoves#readme
Project-URL: Repository, https://github.com/aytugyuruk/biyoves
Keywords: biyometrik,fotoğraf,vesikalık,vize,yapay zeka
Classifier: Development Status :: 5 - Production/Stable
Classifier: Intended Audience :: Developers
Classifier: Topic :: Software Development :: Libraries :: Python Modules
Classifier: Topic :: Multimedia :: Graphics :: Capture :: Digital Camera
Classifier: License :: OSI Approved :: MIT License
Classifier: Programming Language :: Python :: 3
Classifier: Programming Language :: Python :: 3.7
Classifier: Programming Language :: Python :: 3.8
Classifier: Programming Language :: Python :: 3.9
Classifier: Programming Language :: Python :: 3.10
Classifier: Programming Language :: Python :: 3.11
Requires-Python: >=3.7
License-File: LICENSE
Requires-Dist: opencv-python-headless>=4.5.0
Requires-Dist: numpy>=1.19.0
Requires-Dist: onnxruntime>=1.10.0
Dynamic: license-file
